snapbot/__init__.py
snapbot/handlers.py
snapbot/static/handlers.js
snapbot/static/index.js
snapbot-0.0.1a1.dev2.data/data/etc/jupyter/jupyter_notebook_config.d/snapbot.json
snapbot-0.0.1a1.dev2.data/data/etc/jupyter/nbconfig/notebook.d/snapbot.json
snapbot-0.0.1a1.dev2.data/data/share/jupyter/nbextensions/snapbot/handlers.js
snapbot-0.0.1a1.dev2.data/data/share/jupyter/nbextensions/snapbot/index.js
snapbot-0.0.1a1.dev2.dist-info/LICENSE
snapbot-0.0.1a1.dev2.dist-info/METADATA
snapbot-0.0.1a1.dev2.dist-info/WHEEL
snapbot-0.0.1a1.dev2.dist-info/top_level.txt
snapbot-0.0.1a1.dev2.dist-info/RECORD
